litecharts/__init__.py
litecharts/_js.py
litecharts/chart.py
litecharts/convert.py
litecharts/pane.py
litecharts/render.py
litecharts/series.py
litecharts/types.py
litecharts/js/.gitkeep
litecharts/js/__init__.py
litecharts/js/lightweight-charts.js
litecharts/plugins/__init__.py
litecharts/plugins/draw_rectangle.py
litecharts/plugins/marker_tooltips.py
litecharts-0.1.3.dist-info/METADATA
litecharts-0.1.3.dist-info/WHEEL
litecharts-0.1.3.dist-info/licenses/LICENSE
litecharts-0.1.3.dist-info/RECORD
