Metadata-Version: 2.4
Name: litecharts
Version: 0.1.3
Summary: Python wrapper for TradingView Lightweight Charts
Project-URL: Homepage, https://github.com/ChadThackray/litecharts
Project-URL: Repository, https://github.com/ChadThackray/litecharts
Author: Chad Thackray
License-Expression: MIT
License-File: LICENSE
Keywords: candlestick,charts,finance,trading,visualization
Classifier: Development Status :: 3 - Alpha
Classifier: Intended Audience :: Developers
Classifier: Intended Audience :: Financial and Insurance Industry
Classifier: License :: OSI Approved :: MIT License
Classifier: Programming Language :: Python :: 3
Classifier: Programming Language :: Python :: 3.10
Classifier: Programming Language :: Python :: 3.11
Classifier: Programming Language :: Python :: 3.12
Classifier: Programming Language :: Python :: 3.13
Classifier: Topic :: Scientific/Engineering :: Visualization
Classifier: Typing :: Typed
Requires-Python: >=3.10
Provides-Extra: dev
Requires-Dist: mypy>=1.0; extra == 'dev'
Requires-Dist: pandas-stubs>=2.0; extra == 'dev'
Requires-Dist: pytest>=7.0; extra == 'dev'
Requires-Dist: ruff>=0.8; extra == 'dev'
